perceptron_forecaster/__init__.py
perceptron_forecaster/embending.py
perceptron_forecaster/layers.py
perceptron_forecaster-0.1.0.dist-info/LICENSE
perceptron_forecaster-0.1.0.dist-info/METADATA
perceptron_forecaster-0.1.0.dist-info/WHEEL
perceptron_forecaster-0.1.0.dist-info/RECORD
