Metadata-Version: 2.1
Name: perceptron-forecaster
Version: 0.1.0
Summary: 
Author: sambaiga
Author-email: sambaiga@gmail.com
Requires-Python: >=3.11,<4.0
Classifier: Programming Language :: Python :: 3
Classifier: Programming Language :: Python :: 3.11
Classifier: Programming Language :: Python :: 3.12
Requires-Dist: numpy (>=1.26.4,<2.0.0)
Requires-Dist: pytorch-lightning (>=2.2.5,<3.0.0)
Requires-Dist: torch (>=2.3.0,<3.0.0)
Requires-Dist: torchmetrics (>=1.4.0.post0,<2.0.0)
